[{"id": "9127956", "index": 1, "title": "랭킹 1위의 여동생입니다 (228화)", "url": "https://series.naver.com/novel/detail.series?productNo=9127956", "thumb": "https://comicthumb-phinf.pstatic.net/20230324_260/pocket_16796369186742zQSX_JPEG/rank1sis2.jpg?type=m79", "star": "8.2", "author": "리티티"}, {"id": "9583698", "index": 2, "title": "당신과 완벽하게 이별하는 방법 (137화)", "url": "https://series.naver.com/novel/detail.series?productNo=9583698", "thumb": "https://comicthumb-phinf.pstatic.net/20230328_256/pocket_1679995210996xqJ9E_JPEG/%B4%E7%BD%C5%B0%FA%BF%CF%BA%AE%C7%CF%B0%D4%C0%CC%BA%B0%C7%CF%B4%C2%B9%E6%B9%FD_1600x2400.jpg?type=m79", "star": "8.5", "author": "솔탕"}, {"id": "9627917", "index": 3, "title": "그 이름으로 살기 위하여(136화)", "url": "https://series.naver.com/novel/detail.series?productNo=9627917", "thumb": "https://comicthumb-phinf.pstatic.net/20230407_275/pocket_1680851841517vx1o2_JPEG/cover.jpg?type=m79", "star": "8.0", "author": "목련바람"}, {"id": "9770545", "index": 4, "title": "괴물 대공의 시한부 아내가 되었다 (220화)", "url": "https://series.naver.com/novel/detail.series?productNo=9770545", "thumb": "https://comicthumb-phinf.pstatic.net/20230517_175/pocket_1684292276302Tib5q_JPEG/anarchdukeofmonster.jpg?type=m79", "star": "8.5", "author": "진혜이"}, {"id": "9813991", "index": 5, "title": "천대받던 마법명가 손녀딸은 암살천재 (111화)", "url": "https://series.naver.com/novel/detail.series?productNo=9813991", "thumb": "https://comicthumb-phinf.pstatic.net/20230531_235/pocket_1685505123885cmjbX_JPEG/00.jpg?type=m79", "star": "7.1", "author": "연비"}, {"id": "9874787", "index": 6, "title": "내 남편을 죽여 줘 (91화)", "url": "https://series.naver.com/novel/detail.series?productNo=9874787", "thumb": "https://comicthumb-phinf.pstatic.net/20230616_255/pocket_1686896478830SUXy5_JPEG/killmyhb.jpg?type=m79", "star": "7.4", "author": "가람달"}, {"id": "9526778", "index": 7, "title": "목숨만은 살려 주세요(192화)", "url": "https://series.naver.com/novel/detail.series?productNo=9526778", "thumb": "https://comicthumb-phinf.pstatic.net/20230314_151/pocket_1678787770013gKovu_JPEG/%B8%F1%BC%FB%B8%B8%C0%BA%BB%EC%B7%C1%C1%D6%BC%BC%BF%E4_%C5%B8%C0%CC%C6%F7%C3%D6%C1%BE.jpg?type=m79", "star": "8.3", "author": "전어나"}, {"id": "9584089", "index": 8, "title": "파랑새의 목을 꺾으면 (138화)", "url": "https://series.naver.com/novel/detail.series?productNo=9584089", "thumb": "https://comicthumb-phinf.pstatic.net/20230329_124/pocket_1680045862484e5cqc_JPEG/cover.jpg?type=m79", "star": "7.1", "author": "화숙"}, {"id": "9881115", "index": 9, "title": "특급 계약 결혼의 말로 (88화)", "url": "https://series.naver.com/novel/detail.series?productNo=9881115", "thumb": "https://comicthumb-phinf.pstatic.net/20230622_38/pocket_1687418425744KcL7w_JPEG/%C6%AF%B1%DE%B0%E8%BE%E0_%B3%D7%C0%CC%B9%F6%BF%EB.jpg?type=m79", "star": "8.7", "author": "션킴"}, {"id": "9749924", "index": 10, "title": "남편을 죽였다 (114화)", "url": "https://series.naver.com/novel/detail.series?productNo=9749924", "thumb": "https://comicthumb-phinf.pstatic.net/20230510_135/pocket_1683707723444aOxEt_JPEG/killthehb.jpg?type=m79", "star": "7.0", "author": "염장이"}, {"id": "9779829", "index": 11, "title": "악녀의 시집살이는 즐겁다 (125화)", "url": "https://series.naver.com/novel/detail.series?productNo=9779829", "thumb": "https://comicthumb-phinf.pstatic.net/20230519_51/pocket_16844746719351s5G3_JPEG/wickedwfml.jpg?type=m79", "star": "9.1", "author": "준예"}, {"id": "9825454", "index": 12, "title": "오만불손한 나의 그림자 (136화)", "url": "https://series.naver.com/novel/detail.series?productNo=9825454", "thumb": "https://comicthumb-phinf.pstatic.net/20230607_287/pocket_1686115343216Pj7wM_JPEG/510692_100.jpg?type=m79", "star": "8.0", "author": "초코냥이"}, {"id": "9574575", "index": 13, "title": "공녀는 돌아오지 않았다 (226화)", "url": "https://series.naver.com/novel/detail.series?productNo=9574575", "thumb": "https://comicthumb-phinf.pstatic.net/20230327_29/pocket_1679882174821l8DTb_JPEG/%C7%A5%C1%F6-%B0%F8%B3%E0%B4%C2_%B5%B9%BE%C6%BF%C0%C1%F6_%BE%CA%BE%D2%B4%D9.jpg?type=m79", "star": "6.7", "author": "젤라"}, {"id": "9595972", "index": 14, "title": "결국 여주인공이 도망갔다 (147화)", "url": "https://series.naver.com/novel/detail.series?productNo=9595972", "thumb": "https://comicthumb-phinf.pstatic.net/20230330_121/pocket_1680163432772HGvLL_JPEG/cover.jpg?type=m79", "star": "7.7", "author": "톰히"}, {"id": "9722320", "index": 15, "title": "왕관은 마녀의 손에 (173화)", "url": "https://series.naver.com/novel/detail.series?productNo=9722320", "thumb": "https://comicthumb-phinf.pstatic.net/20230502_232/pocket_1683019577255g3IK9_JPEG/handsofthewitch.jpg?type=m79", "star": "7.1", "author": "은솔"}, {"id": "9860984", "index": 16, "title": "빼앗길 바엔 빼앗아 버리겠다 (94화)", "url": "https://series.naver.com/novel/detail.series?productNo=9860984", "thumb": "https://comicthumb-phinf.pstatic.net/20230613_141/pocket_1686622929213J4Eff_JPEG/divtofdepr.jpg?type=m79", "star": "8.6", "author": "뮤지개"}, {"id": "9785187", "index": 17, "title": "사랑하는 당신에게, 나의 황홀한 악몽을 드립니다 (111화)", "url": "https://series.naver.com/novel/detail.series?productNo=9785187", "thumb": "https://comicthumb-phinf.pstatic.net/20230522_205/pocket_1684737561992UcVdE_JPEG/%BA%E4%C4%C4%C1%EE_%BB%E7%B6%FB%C7%CF%B4%C2_%B4%E7%BD%C5%BF%A1%B0%D4_%BD%C3%C1%A4%BF%AC_%C7%A5%C1%F6_%BC%F6%C1%A4%BE%C8.jpg?type=m79", "star": "7.4", "author": "스캠퍼"}, {"id": "9881459", "index": 18, "title": "죽은 악녀는 남주의 아이를 가졌다 (86화)", "url": "https://series.naver.com/novel/detail.series?productNo=9881459", "thumb": "https://comicthumb-phinf.pstatic.net/20230619_154/pocket_1687161833640rv98a_JPEG/%C1%D7%C0%BA_%BE%C7%B3%E0%B4%C2_%B3%B2%C1%D6%C0%C7_%BE%C6%C0%CC%B8%A6_%B0%A1%C1%B3%B4%D9_%BD%C3%B8%AE%C1%EE_%BF%A1%B5%F0%BC%C7%BF%EB.jpg?type=m79", "star": "7.6", "author": "광산김파도"}, {"id": "9662852", "index": 19, "title": "침묵의 모란이 필 때 (154화)", "url": "https://series.naver.com/novel/detail.series?productNo=9662852", "thumb": "https://comicthumb-phinf.pstatic.net/20230526_174/pocket_1685082432719fU2dU_JPEG/505560_139.jpg?type=m79", "star": "8.3", "author": "스캠퍼"}, {"id": "9778090", "index": 20, "title": "S급 드래곤은 마스코트가 되기로 했다 (110화)", "url": "https://series.naver.com/novel/detail.series?productNo=9778090", "thumb": "https://comicthumb-phinf.pstatic.net/20230518_208/pocket_1684406450006Odj9B_JPEG/S%B1%DE%B5%E5%B7%A1%B0%EF%C0%BA%B8%B6%BD%BA%C4%DA%C6%AE%B0%A1%B5%C7%B1%E2%B7%CE%C7%DF%B4%D9_%C0%FC%C0%DA%C3%A5%C7%A5%C1%F6_%C3%D6%C1%BE.jpg?type=m79", "star": "8.9", "author": "전국햄스터협회장"}, {"id": "9799407", "index": 21, "title": "대공의 치료제로 죽을 운명입니다 (90화)", "url": "https://series.naver.com/novel/detail.series?productNo=9799407", "thumb": "https://comicthumb-phinf.pstatic.net/20230524_154/pocket_1684916965589oxKlP_JPEG/%B4%EB%B0%F8%C0%C7%C4%A1%B7%E1%C1%A6%B7%CE%C1%D7%C0%BB%BF%EE%B8%ED%C0%D4%B4%CF%B4%D9.jpg?type=m79", "star": "8.1", "author": "박백구"}, {"id": "9690534", "index": 22, "title": "새엄마로 간택당했습니다 (116화)", "url": "https://series.naver.com/novel/detail.series?productNo=9690534", "thumb": "https://comicthumb-phinf.pstatic.net/20230424_42/pocket_1682302325297EzQlB_JPEG/cover.jpg?type=m79", "star": "8.1", "author": "이뚜언"}, {"id": "9737272", "index": 23, "title": "긍지 높은 지오힐데를 위하여 (114화)", "url": "https://series.naver.com/novel/detail.series?productNo=9737272", "thumb": "https://comicthumb-phinf.pstatic.net/20230516_136/pocket_16842018052510HpR6_JPEG/%B1%E0%C1%F6%B3%F4%C0%BA_%C1%F6%BF%C0%C8%FA%B5%A5%B8%A6_%C0%A7%C7%CF%BF%A9_%BD%C3%B8%AE%C1%EE_%BB%E7%C0%CC%C1%EE.jpg?type=m79", "star": "8.8", "author": "그고자자"}, {"id": "9875969", "index": 24, "title": "달아나지 않도록 더 세게 (133화)", "url": "https://series.naver.com/novel/detail.series?productNo=9875969", "thumb": "https://comicthumb-phinf.pstatic.net/20230616_195/pocket_16869027930490SPTh_JPEG/0000_2.jpg?type=m79", "star": "8.4", "author": "도토리"}, {"id": "9823963", "index": 25, "title": "가짜 공작 부부의 은밀한 사정 (109화)", "url": "https://series.naver.com/novel/detail.series?productNo=9823963", "thumb": "https://comicthumb-phinf.pstatic.net/20230601_43/pocket_1685607052033z0ytf_JPEG/%B0%A1%C2%A5_%B0%F8%C0%DB%BA%CE%BA%CE%C0%C7_%C0%BA%B9%D0%C7%D1_%BB%E7%C1%A4_%C5%B8%C0%CC%C6%B2_%C3%D6%C1%BE.jpg?type=m79", "star": "7.5", "author": "이인혜"}]