[{"id": "9397472", "index": 1, "title": "원작 속 악녀와 남주를 이어 주었더니 (104화)", "url": "https://series.naver.com/novel/detail.series?productNo=9397472", "thumb": "https://comicthumb-phinf.pstatic.net/20230210_276/pocket_1676010159015TdK62_JPEG/%BF%F8%C0%DB_%BC%D3_%BE%C7%B3%E0%BF%CD_%B3%B2%C1%D6%B8%A6_%C0%CC%BE%EE_%C1%D6%BE%FA%B4%F5%B4%CF_%C5%B8%C0%CC%C6%B2_mix5.jpg?type=m79", "star": "7.5", "author": "현이경"}, {"id": "9193908", "index": 2, "title": "바람은 붙잡을 수 없다 (144화)", "url": "https://series.naver.com/novel/detail.series?productNo=9193908", "thumb": "https://comicthumb-phinf.pstatic.net/20230307_298/pocket_1678154368366xj9ia_JPEG/%B9%D9%B6%F7%C0%BA_%BA%D9%C0%E2%C0%BB_%BC%F6_%BE%F8%B4%D9_2%BA%CE_%C5%B8%C0%CC%C6%B2_%C3%D6%C1%BE_%B8%AE%BB%E7%C0%CC%C2%A1%28650x855%29.jpg?type=m79", "star": "8.5", "author": "유이란"}, {"id": "4077568", "index": 3, "title": "모스크바의 여명 (1228화)", "url": "https://series.naver.com/novel/detail.series?productNo=4077568", "thumb": "https://comicthumb-phinf.pstatic.net/20190403_255/pocket_1554277665901LD4IV_JPEG/mmm.jpg?type=m79", "star": "9.5", "author": "황장미"}, {"id": "9080689", "index": 4, "title": "쉿, 그 가이드를 빡치게 하지마! (159화)", "url": "https://series.naver.com/novel/detail.series?productNo=9080689", "thumb": "https://comicthumb-phinf.pstatic.net/20221124_108/pocket_1669273353898dzYYu_JPEG/%BD%B2%2C-%B1%D7-%B0%A1%C0%CC%B5%E5%B8%A6-%BA%FD%C4%A1%B0%D4-%C7%CF%C1%F6%B8%B6_%C7%A5%C1%F6.jpg?type=m79", "star": "8.0", "author": "은빛을담은별"}, {"id": "9158663", "index": 5, "title": "버려진 악녀는 레스토랑을 꿈꾼다 (138화)", "url": "https://series.naver.com/novel/detail.series?productNo=9158663", "thumb": "https://comicthumb-phinf.pstatic.net/20221202_299/pocket_1669961000619ti7FI_JPEG/%B9%F6%B7%C1%C1%F8%BE%C7%B3%E0%B4%C2%B7%B9%BD%BA%C5%E4%B6%FB%C0%BB%B2%DE%B2%DB%B4%D9_%C7%A5%C1%F6_%C4%C1%C5%D9%C3%F7%C1%A6%C0%DB%BF%EB%28720x1033%29.jpg?type=m79", "star": "8.5", "author": "블루밍캔디"}, {"id": "9454228", "index": 6, "title": "그 대공은 모든 것을 앗아갔다 (91화)", "url": "https://series.naver.com/novel/detail.series?productNo=9454228", "thumb": "https://comicthumb-phinf.pstatic.net/20230224_102/pocket_1677207208600YKHk5_JPEG/%B1%D7%B4%EB%B0%F8%C0%BA_%B8%F0%B5%E7%B0%CD%C0%BB_%C3%D6%C1%BE_%C5%B8%C0%CC%C6%B2%28700px%29.jpg?type=m79", "star": "8.0", "author": "쑥쥬"}, {"id": "9479410", "index": 7, "title": "악당 가문의 금지옥엽이 되었는데 (80화)", "url": "https://series.naver.com/novel/detail.series?productNo=9479410", "thumb": "https://comicthumb-phinf.pstatic.net/20230303_53/pocket_1677808116666gCVSN_JPEG/%BE%C7%B4%E7_%B0%A1%B9%AE%C0%C7_%B1%DD%C1%F6%BF%C1%BF%B1%C0%CC_%B5%C7%BE%FA%B4%C2%B5%A5_%C3%D6%C1%BE.jpg?type=m79", "star": "9.2", "author": "햇노랑"}, {"id": "9050291", "index": 8, "title": "그 계약결혼은 분명 공평했다 (136화)", "url": "https://series.naver.com/novel/detail.series?productNo=9050291", "thumb": "https://comicthumb-phinf.pstatic.net/20221101_203/pocket_1667286487259IColh_JPEG/220928_%B9%DA%B0%A1%BA%A7_%B1%D7_%B0%E8%BE%E0%B0%E1%C8%A5%C0%BA_%BA%D0%B8%ED_%B0%F8%C6%F2%C7%DF%B4%D9_%C3%D6%C1%BE.jpg?type=m79", "star": "9.0", "author": "박가벨"}, {"id": "9216728", "index": 9, "title": "다시 태어나도 악녀는 악녀다 (130화)", "url": "https://series.naver.com/novel/detail.series?productNo=9216728", "thumb": "https://comicthumb-phinf.pstatic.net/20221220_201/pocket_1671511729715KJQV6_JPEG/%B4%D9%BD%C3_%C5%C2%BE%EE%B3%AA%B5%B5_%BE%C7%B3%E0%B4%C2_%BE%C7%B3%E0%B4%D9_%C3%D6%C1%BE%BA%BB%28%BF%AC%C0%E7%29.jpg?type=m79", "star": "7.8", "author": "하물성"}, {"id": "8860467", "index": 10, "title": "늑대를 삼킨 공녀님 (151화)", "url": "https://series.naver.com/novel/detail.series?productNo=8860467", "thumb": "https://comicthumb-phinf.pstatic.net/20220907_278/pocket_1662525709415WwjgY_JPEG/15.jpg?type=m79", "star": "7.9", "author": "으넹나무"}, {"id": "9232429", "index": 11, "title": "악당의 가짜 여동생이 되었습니다 (102화)", "url": "https://series.naver.com/novel/detail.series?productNo=9232429", "thumb": "https://comicthumb-phinf.pstatic.net/20221223_213/pocket_16717749538149GDna_JPEG/00.jpg?type=m79", "star": "7.6", "author": "채론도"}, {"id": "9171942", "index": 12, "title": "계략 남편의 집착에 걸려들었다 (123화)", "url": "https://series.naver.com/novel/detail.series?productNo=9171942", "thumb": "https://comicthumb-phinf.pstatic.net/20221207_43/pocket_1670392751373qLph2_JPEG/%B0%E8%B7%AB%B3%B2%C6%ED_%C0%CC%C6%E0%C7%A5%C1%F6%C3%D6%C1%BE.jpg?type=m79", "star": "8.3", "author": "피유리"}, {"id": "3975895", "index": 13, "title": "푸른 밤, 황홀의 윤무 (809화)", "url": "https://series.naver.com/novel/detail.series?productNo=3975895", "thumb": "https://comicthumb-phinf.pstatic.net/20190218_255/pocket_1550475731679uoqQE_JPEG/ronde_in_raptures_cover.jpg?type=m79", "star": "9.6", "author": "유안나"}, {"id": "9352189", "index": 14, "title": "당신의 구원이 나를 죽이려 할 때 (111화)", "url": "https://series.naver.com/novel/detail.series?productNo=9352189", "thumb": "https://comicthumb-phinf.pstatic.net/20230208_124/pocket_1675836248541xYIqX_JPEG/cover.jpg?type=m79", "star": "7.5", "author": "돈미몽"}, {"id": "9492339", "index": 15, "title": "황제 폐하의 말 못 할 고민(29화완결)", "url": "https://series.naver.com/novel/detail.series?productNo=9492339", "thumb": "https://ssl.pstatic.net/static/nstore/thumb/19over_book2_79x119.gif", "star": "10.0", "author": "책도둑"}, {"id": "9537690", "index": 16, "title": "기란(135화완결)", "url": "https://series.naver.com/novel/detail.series?productNo=9537690", "thumb": "https://comicthumb-phinf.pstatic.net/20230316_72/pocket_1678952114069RSSSG_JPEG/%C6%C4%B6%F5%B9%CC%B5%F0%BE%EE_%B1%E2%B6%F51_%C7%A5%C1%F6.jpg?type=m79", "star": "0.0", "author": "비연"}, {"id": "9037007", "index": 17, "title": "첫사랑 수업(176화완결)", "url": "https://series.naver.com/novel/detail.series?productNo=9037007", "thumb": "https://comicthumb-phinf.pstatic.net/20221116_294/pocket_1668570577692ALKhH_JPEG/cover.jpg?type=m79", "star": "7.9", "author": "닷새datsae"}, {"id": "9196915", "index": 18, "title": "대공님, 이러시면 죽일 수가 없잖아요 (132화)", "url": "https://series.naver.com/novel/detail.series?productNo=9196915", "thumb": "https://comicthumb-phinf.pstatic.net/20221214_120/pocket_1670984427330HhpWz_JPEG/%B4%EB%B0%F8%B4%D4-%C0%CC%B7%AF%BD%C3%B8%E9-%C1%D7%C0%CF%BC%F6%B0%A1-%BE%F8%C0%DD%BE%C6%BF%E4_%C7%A5%C1%F6%28720x1033%29.jpg?type=m79", "star": "7.8", "author": "마거릿점례"}, {"id": "9246745", "index": 19, "title": "파멸 속에서 나를 구원하소서 (131화)", "url": "https://series.naver.com/novel/detail.series?productNo=9246745", "thumb": "https://comicthumb-phinf.pstatic.net/20221228_20/pocket_16722165674331rTnS_JPEG/%C6%C4%B8%EA_2.jpg?type=m79", "star": "7.2", "author": "하이픈"}, {"id": "9521092", "index": 20, "title": "가짜 황후 (77화)", "url": "https://series.naver.com/novel/detail.series?productNo=9521092", "thumb": "https://comicthumb-phinf.pstatic.net/20230313_228/pocket_1678706346971ctNHz_JPEG/%C1%A6%B8%F1_%BE%F8%C0%BD.jpg?type=m79", "star": "7.7", "author": "성화영"}, {"id": "9346568", "index": 21, "title": "내 젤리를 너에게 바친다 (96화)", "url": "https://series.naver.com/novel/detail.series?productNo=9346568", "thumb": "https://comicthumb-phinf.pstatic.net/20230127_127/pocket_1674778899756HR9QO_JPEG/%A1%DA%C1%A9%B3%CA%B9%D9_%C3%D6%C1%BE_%C7%A5%C1%F6.jpg?type=m79", "star": "8.8", "author": "감규울"}, {"id": "9284157", "index": 22, "title": "에디나 생존기 (158화)", "url": "https://series.naver.com/novel/detail.series?productNo=9284157", "thumb": "https://comicthumb-phinf.pstatic.net/20230109_246/pocket_1673248742419MLVtW_JPEG/cover.jpg?type=m79", "star": "9.0", "author": "sion"}, {"id": "9443321", "index": 23, "title": "전남편의 정부가 된 건에 관하여 (95화)", "url": "https://series.naver.com/novel/detail.series?productNo=9443321", "thumb": "https://comicthumb-phinf.pstatic.net/20230312_244/pocket_167860534765235cWx_JPEG/%C7%A5%C1%F6.jpg?type=m79", "star": "7.7", "author": "디버스 대도서관"}, {"id": "9389968", "index": 24, "title": "짝사랑은 끝났으니 알아서들 하세요 (99화)", "url": "https://series.naver.com/novel/detail.series?productNo=9389968", "thumb": "https://comicthumb-phinf.pstatic.net/20230209_103/pocket_1675910135445Bnsbh_JPEG/cover.jpg?type=m79", "star": "7.6", "author": "스크류뿅뿅"}, {"id": "9414169", "index": 25, "title": "당신은 불장난일 뿐 (158화)", "url": "https://series.naver.com/novel/detail.series?productNo=9414169", "thumb": "https://comicthumb-phinf.pstatic.net/20230216_257/pocket_1676479779472Eba6I_JPEG/KakaoTalk_20230216_014631173.jpg?type=m79", "star": "9.0", "author": "새뉴"}]